ectoolkits/__init__.py
ectoolkits/log.py
ectoolkits/analysis/__init__.py
ectoolkits/analysis/acidity.py
ectoolkits/analysis/atom_density.py
ectoolkits/analysis/band_align.py
ectoolkits/analysis/dielectric_constant.py
ectoolkits/analysis/disdeg.py
ectoolkits/analysis/finite_size_correction.py
ectoolkits/analysis/proton_transfer_cv.py
ectoolkits/analysis/reweight.py
ectoolkits/analysis/rutile110.py
ectoolkits/analysis/uncertainty.py
ectoolkits/analysis/water.py
ectoolkits/cli/cmd.py
ectoolkits/matplotlibstyle/__init__.py
ectoolkits/matplotlibstyle/jcp.mplstyle
ectoolkits/matplotlibstyle/project.mplstyle
ectoolkits/matplotlibstyle/yb-paper.mplstyle
ectoolkits/plots/__init__.py
ectoolkits/plots/band_align.py
ectoolkits/plots/dpmd.py
ectoolkits/structures/__init__.py
ectoolkits/structures/interface.py
ectoolkits/structures/rutile110.py
ectoolkits/structures/slab.py
ectoolkits/structures/tools.py
ectoolkits/utils/__init__.py
ectoolkits/utils/math.py
ectoolkits/utils/rutile110.py
ectoolkits/utils/utils.py
ectoolkits/utils/vasp.py
ectoolkits/workflows/calc_diel.py
ectoolkits-0.4.4.dist-info/licenses/LICENSE
ectoolkits-0.4.4.dist-info/METADATA
ectoolkits-0.4.4.dist-info/WHEEL
ectoolkits-0.4.4.dist-info/entry_points.txt
ectoolkits-0.4.4.dist-info/top_level.txt
ectoolkits-0.4.4.dist-info/RECORD
