Metadata-Version: 2.4
Name: ECToolkits
Version: 0.4.4
Summary: ElectroChemical Toolkit(ECToolkit), the package to calculate electrochemical results from atomistic simulations.
Author-email: Yong-Bin Zhuang <robinzhuang@outlook.com>
License:                    GNU LESSER GENERAL PUBLIC LICENSE
Classifier: Programming Language :: Python :: 3.8
Classifier: Programming Language :: Python :: 3.9
Classifier: Programming Language :: Python :: 3.10
Classifier: License :: OSI Approved :: GNU Library or Lesser General Public License (LGPL)
Requires-Python: >=3.8
License-File: LICENSE
Requires-Dist: numpy<=1.24.4
Requires-Dist: gsd<=3.2.1
Requires-Dist: matplotlib>=3.3.2
Requires-Dist: ase>=3.20.1
Requires-Dist: cp2kdata>=0.6.1
Requires-Dist: pandas
Requires-Dist: MDAnalysis>=2.1.0
Requires-Dist: dpdispatcher
Requires-Dist: cp2k-input-tools
Requires-Dist: pyyaml
Requires-Dist: rdkit
Dynamic: license-file
